[
  {
    "name": "Acanthaceae",
    "latin": "Acanthus family",
    "plants": [
      {
        "slug": "andrographis",
        "name": "Andrographis"
      }
    ],
    "slug": "acanthaceae"
  },
  {
    "name": "Adoxaceae",
    "latin": "formerly Caprifoliaceae",
    "plants": [
      {
        "slug": "elderberry",
        "name": "Elderberry"
      }
    ],
    "slug": "adoxaceae"
  },
  {
    "name": "Aizoaceae",
    "latin": "Ice Plant family",
    "plants": [
      {
        "slug": "kanna",
        "name": "Kanna"
      }
    ],
    "slug": "aizoaceae"
  },
  {
    "name": "Amaryllidaceae",
    "latin": "Amaryllis family, formerly Liliaceae",
    "plants": [
      {
        "slug": "garlic",
        "name": "Garlic"
      }
    ],
    "slug": "amaryllidaceae"
  },
  {
    "name": "Apiaceae",
    "latin": "Carrot/Parsley family",
    "plants": [
      {
        "slug": "angelica",
        "name": "Angelica"
      },
      {
        "slug": "ashitaba",
        "name": "Ashitaba"
      },
      {
        "slug": "celery-seed",
        "name": "Celery Seed"
      },
      {
        "slug": "coriander",
        "name": "Coriander"
      },
      {
        "slug": "cumin",
        "name": "Cumin"
      },
      {
        "slug": "dill",
        "name": "Dill"
      },
      {
        "slug": "dong-quai",
        "name": "Dong Quai"
      },
      {
        "slug": "fennel",
        "name": "Fennel"
      },
      {
        "slug": "gotu-kola",
        "name": "Gotu Kola"
      },
      {
        "slug": "lomatium",
        "name": "Lomatium"
      },
      {
        "slug": "osha",
        "name": "Osha"
      },
      {
        "slug": "parsley",
        "name": "Parsley"
      }
    ],
    "slug": "apiaceae"
  },
  {
    "name": "Apocynaceae",
    "latin": "Dogbane family",
    "plants": [
      {
        "slug": "gymnema",
        "name": "Gymnema"
      },
      {
        "slug": "hoodia",
        "name": "Hoodia"
      }
    ],
    "slug": "apocynaceae"
  },
  {
    "name": "Aquifoliaceae",
    "latin": "Holly family",
    "plants": [
      {
        "slug": "guayusa",
        "name": "Guayusa"
      },
      {
        "slug": "yerba-mate",
        "name": "Yerba Mate"
      }
    ],
    "slug": "aquifoliaceae"
  },
  {
    "name": "Araliaceae",
    "latin": "Ginseng family",
    "plants": [
      {
        "slug": "eleuthero",
        "name": "Eleuthero"
      },
      {
        "slug": "ginseng",
        "name": "Ginseng"
      }
    ],
    "slug": "araliaceae"
  },
  {
    "name": "Arecaceae",
    "latin": "Palm family",
    "plants": [
      {
        "slug": "acai",
        "name": "Acai"
      },
      {
        "slug": "saw-palmetto",
        "name": "Saw Palmetto"
      }
    ],
    "slug": "arecaceae"
  },
  {
    "name": "Asparagaceae",
    "latin": "Asparagus family",
    "plants": [
      {
        "slug": "shatavari",
        "name": "Shatavari"
      }
    ],
    "slug": "asparagaceae"
  },
  {
    "name": "Asphodelaceae",
    "latin": "Asphodel family, formerly Liliaceae",
    "plants": [
      {
        "slug": "aloe-vera",
        "name": "Aloe Vera"
      }
    ],
    "slug": "asphodelaceae"
  },
  {
    "name": "Asteraceae",
    "latin": "Sunflower/Daisy family",
    "plants": [
      {
        "slug": "arnica",
        "name": "Arnica"
      },
      {
        "slug": "bhringaraj",
        "name": "Bhringaraj"
      },
      {
        "slug": "blessed-thistle",
        "name": "Blessed Thistle"
      },
      {
        "slug": "burdock",
        "name": "Burdock"
      },
      {
        "slug": "calendula",
        "name": "Calendula"
      },
      {
        "slug": "chamomile",
        "name": "Chamomile"
      },
      {
        "slug": "coltsfoot",
        "name": "Coltsfoot"
      },
      {
        "slug": "dandelion",
        "name": "Dandelion"
      },
      {
        "slug": "echinacea",
        "name": "Echinacea"
      },
      {
        "slug": "elecampane",
        "name": "Elecampane"
      },
      {
        "slug": "gravel-root",
        "name": "Gravel Root"
      },
      {
        "slug": "milk-thistle",
        "name": "Milk Thistle"
      },
      {
        "slug": "mugwort",
        "name": "Mugwort"
      },
      {
        "slug": "spilanthes",
        "name": "Spilanthes / Toothache Plant"
      },
      {
        "slug": "wormwood",
        "name": "Wormwood"
      },
      {
        "slug": "yarrow",
        "name": "Yarrow"
      }
    ],
    "slug": "asteraceae"
  },
  {
    "name": "Berberidaceae",
    "latin": "Barberry family",
    "plants": [
      {
        "slug": "blue-cohosh",
        "name": "Blue Cohosh"
      },
      {
        "slug": "oregon-grape",
        "name": "Oregon Grape"
      }
    ],
    "slug": "berberidaceae"
  },
  {
    "name": "Betulaceae",
    "latin": "Birch family",
    "plants": [
      {
        "slug": "birch",
        "name": "Birch"
      }
    ],
    "slug": "betulaceae"
  },
  {
    "name": "Bignoniaceae",
    "latin": "Trumpet Vine family",
    "plants": [
      {
        "slug": "pau-d-arco",
        "name": "Pau D'Arco"
      }
    ],
    "slug": "bignoniaceae"
  },
  {
    "name": "Boraginaceae",
    "latin": "Borage family",
    "plants": [
      {
        "slug": "borage",
        "name": "Borage"
      },
      {
        "slug": "comfrey",
        "name": "Comfrey"
      }
    ],
    "slug": "boraginaceae"
  },
  {
    "name": "Brassicaceae",
    "latin": "Mustard family",
    "plants": [
      {
        "slug": "maca",
        "name": "Maca"
      }
    ],
    "slug": "brassicaceae"
  },
  {
    "name": "Campanulaceae",
    "latin": "Bellflower family",
    "plants": [
      {
        "slug": "codonopsis",
        "name": "Codonopsis"
      }
    ],
    "slug": "campanulaceae"
  },
  {
    "name": "Cannabaceae",
    "latin": "Hemp family",
    "plants": [
      {
        "slug": "hemp-cbd",
        "name": "Hemp / CBD"
      },
      {
        "slug": "hops",
        "name": "Hops"
      }
    ],
    "slug": "cannabaceae"
  },
  {
    "name": "Caprifoliaceae",
    "latin": "Honeysuckle family, formerly Valerianaceae",
    "plants": [
      {
        "slug": "valerian",
        "name": "Valerian"
      }
    ],
    "slug": "caprifoliaceae"
  },
  {
    "name": "Caryophyllaceae",
    "latin": "Pink family",
    "plants": [
      {
        "slug": "chickweed",
        "name": "Chickweed"
      }
    ],
    "slug": "caryophyllaceae"
  },
  {
    "name": "Chlorellaceae",
    "latin": "Green microalgae family",
    "plants": [
      {
        "slug": "chlorella",
        "name": "Chlorella"
      }
    ],
    "slug": "chlorellaceae"
  },
  {
    "name": "Clusiaceae",
    "latin": "Mangosteen family",
    "plants": [
      {
        "slug": "mangosteen",
        "name": "Mangosteen"
      }
    ],
    "slug": "clusiaceae"
  },
  {
    "name": "Combretaceae",
    "latin": "White mangrove family",
    "plants": [
      {
        "slug": "arjuna",
        "name": "Arjuna"
      },
      {
        "slug": "terminalia-chebula",
        "name": "Haritaki / Black Myrobalan (Triphala representative)"
      }
    ],
    "slug": "combretaceae"
  },
  {
    "name": "Cordycipitaceae",
    "latin": "Cordyceps family",
    "plants": [
      {
        "slug": "cordyceps",
        "name": "Cordyceps"
      }
    ],
    "slug": "cordycipitaceae"
  },
  {
    "name": "Crassulaceae",
    "latin": "Stonecrop family",
    "plants": [
      {
        "slug": "rhodiola",
        "name": "Rhodiola"
      }
    ],
    "slug": "crassulaceae"
  },
  {
    "name": "Cucurbitaceae",
    "latin": "Gourd / Cucumber family",
    "plants": [
      {
        "slug": "bitter-melon",
        "name": "Bitter Melon"
      },
      {
        "slug": "jiaogulan",
        "name": "Jiaogulan"
      }
    ],
    "slug": "cucurbitaceae"
  },
  {
    "name": "Cupressaceae",
    "latin": "Cypress family",
    "plants": [
      {
        "slug": "juniper",
        "name": "Juniper"
      }
    ],
    "slug": "cupressaceae"
  },
  {
    "name": "Dioscoreaceae",
    "latin": "Yam family",
    "plants": [
      {
        "slug": "wild-yam",
        "name": "Wild Yam"
      }
    ],
    "slug": "dioscoreaceae"
  },
  {
    "name": "Elaeagnaceae",
    "latin": "Oleaster family",
    "plants": [
      {
        "slug": "sea-buckthorn",
        "name": "Sea Buckthorn"
      }
    ],
    "slug": "elaeagnaceae"
  },
  {
    "name": "Equisetaceae",
    "latin": "Horsetail family",
    "plants": [
      {
        "slug": "horsetail",
        "name": "Horsetail"
      }
    ],
    "slug": "equisetaceae"
  },
  {
    "name": "Ericaceae",
    "latin": "Heath family",
    "plants": [
      {
        "slug": "cranberry",
        "name": "Cranberry"
      },
      {
        "slug": "uva-ursi",
        "name": "Uva Ursi"
      },
      {
        "slug": "wintergreen",
        "name": "Wintergreen"
      }
    ],
    "slug": "ericaceae"
  },
  {
    "name": "Fabaceae",
    "latin": "Legume / Pea family",
    "plants": [
      {
        "slug": "alfalfa",
        "name": "Alfalfa"
      },
      {
        "slug": "astragalus",
        "name": "Astragalus"
      },
      {
        "slug": "fenugreek",
        "name": "Fenugreek"
      },
      {
        "slug": "licorice",
        "name": "Licorice"
      },
      {
        "slug": "red-clover",
        "name": "Red Clover"
      },
      {
        "slug": "rooibos",
        "name": "Rooibos"
      }
    ],
    "slug": "fabaceae"
  },
  {
    "name": "Fagaceae",
    "latin": "Beech family",
    "plants": [
      {
        "slug": "oak",
        "name": "Oak"
      }
    ],
    "slug": "fagaceae"
  },
  {
    "name": "Ganodermataceae",
    "latin": "Polypore family",
    "plants": [
      {
        "slug": "reishi-mushroom",
        "name": "Reishi Mushroom"
      }
    ],
    "slug": "ganodermataceae"
  },
  {
    "name": "Geraniaceae",
    "latin": "Geranium family",
    "plants": [
      {
        "slug": "pelargonium-sidoides",
        "name": "Pelargonium / Umckaloabo"
      }
    ],
    "slug": "geraniaceae"
  },
  {
    "name": "Ginkgoaceae",
    "latin": "sole member of its family",
    "plants": [
      {
        "slug": "ginkgo",
        "name": "Ginkgo"
      }
    ],
    "slug": "ginkgoaceae"
  },
  {
    "name": "Hamamelidaceae",
    "latin": "Witch hazel family",
    "plants": [
      {
        "slug": "witch-hazel",
        "name": "Witch Hazel"
      }
    ],
    "slug": "hamamelidaceae"
  },
  {
    "name": "Hericiaceae",
    "latin": "Lion's mane family",
    "plants": [
      {
        "slug": "lions-mane",
        "name": "Lion's Mane"
      }
    ],
    "slug": "hericiaceae"
  },
  {
    "name": "Hydrophyllaceae",
    "latin": "Waterleaf family",
    "plants": [
      {
        "slug": "yerba-santa",
        "name": "Yerba Santa"
      }
    ],
    "slug": "hydrophyllaceae"
  },
  {
    "name": "Hypericaceae",
    "latin": "St. John's Wort family",
    "plants": [
      {
        "slug": "st-john-s-wort",
        "name": "St. John's Wort"
      }
    ],
    "slug": "hypericaceae"
  },
  {
    "name": "Juglandaceae",
    "latin": "Walnut family",
    "plants": [
      {
        "slug": "black-walnut",
        "name": "Black Walnut"
      }
    ],
    "slug": "juglandaceae"
  },
  {
    "name": "Lamiaceae",
    "latin": "Mint family",
    "plants": [
      {
        "slug": "basil",
        "name": "Basil"
      },
      {
        "slug": "cats-whiskers-java-tea",
        "name": "Cat's Whiskers / Java Tea"
      },
      {
        "slug": "catnip",
        "name": "Catnip"
      },
      {
        "slug": "chaste-tree",
        "name": "Chaste Tree"
      },
      {
        "slug": "coleus-forskohlii",
        "name": "Coleus / Forskolin"
      },
      {
        "slug": "holy-basil",
        "name": "Holy Basil"
      },
      {
        "slug": "lavender",
        "name": "Lavender"
      },
      {
        "slug": "lemon-balm",
        "name": "Lemon Balm"
      },
      {
        "slug": "motherwort",
        "name": "Motherwort"
      },
      {
        "slug": "oregano",
        "name": "Oregano"
      },
      {
        "slug": "peppermint",
        "name": "Peppermint"
      },
      {
        "slug": "rosemary",
        "name": "Rosemary"
      },
      {
        "slug": "sage",
        "name": "Sage"
      },
      {
        "slug": "self-heal",
        "name": "Self-Heal"
      },
      {
        "slug": "skullcap",
        "name": "Skullcap"
      },
      {
        "slug": "spearmint",
        "name": "Spearmint"
      },
      {
        "slug": "thyme",
        "name": "Thyme"
      },
      {
        "slug": "wood-betony",
        "name": "Wood Betony"
      }
    ],
    "slug": "lamiaceae"
  },
  {
    "name": "Lauraceae",
    "latin": "Laurel family",
    "plants": [
      {
        "slug": "cinnamon",
        "name": "Cinnamon"
      },
      {
        "slug": "sassafras",
        "name": "Sassafras"
      }
    ],
    "slug": "lauraceae"
  },
  {
    "name": "Malvaceae",
    "latin": "Mallow family",
    "plants": [
      {
        "slug": "cacao",
        "name": "Cacao"
      },
      {
        "slug": "hibiscus",
        "name": "Hibiscus"
      },
      {
        "slug": "linden",
        "name": "Linden / Tilia"
      },
      {
        "slug": "marshmallow",
        "name": "Marshmallow"
      }
    ],
    "slug": "malvaceae"
  },
  {
    "name": "Meliaceae",
    "latin": "Mahogany family",
    "plants": [
      {
        "slug": "neem",
        "name": "Neem"
      }
    ],
    "slug": "meliaceae"
  },
  {
    "name": "Menispermaceae",
    "latin": "Moonseed family",
    "plants": [
      {
        "slug": "guduchi",
        "name": "Guduchi / Giloy"
      }
    ],
    "slug": "menispermaceae"
  },
  {
    "name": "Moringaceae",
    "latin": "Moringa family",
    "plants": [
      {
        "slug": "moringa",
        "name": "Moringa"
      }
    ],
    "slug": "moringaceae"
  },
  {
    "name": "Myristicaceae",
    "latin": "Nutmeg family",
    "plants": [
      {
        "slug": "nutmeg",
        "name": "Nutmeg"
      }
    ],
    "slug": "myristicaceae"
  },
  {
    "name": "Myrtaceae",
    "latin": "Myrtle family",
    "plants": [
      {
        "slug": "clove",
        "name": "Clove"
      }
    ],
    "slug": "myrtaceae"
  },
  {
    "name": "Onagraceae",
    "latin": "Evening primrose family",
    "plants": [
      {
        "slug": "evening-primrose",
        "name": "Evening Primrose"
      }
    ],
    "slug": "onagraceae"
  },
  {
    "name": "Orchidaceae",
    "latin": "Orchid family",
    "plants": [
      {
        "slug": "vanilla",
        "name": "Vanilla"
      }
    ],
    "slug": "orchidaceae"
  },
  {
    "name": "Orobanchaceae",
    "latin": "Broomrape family",
    "plants": [
      {
        "slug": "rehmannia",
        "name": "Rehmannia"
      }
    ],
    "slug": "orobanchaceae"
  },
  {
    "name": "Paeoniaceae",
    "latin": "Peony family",
    "plants": [
      {
        "slug": "white-peony",
        "name": "White Peony Root"
      }
    ],
    "slug": "paeoniaceae"
  },
  {
    "name": "Papaveraceae",
    "latin": "Poppy family",
    "plants": [
      {
        "slug": "bloodroot",
        "name": "Bloodroot"
      }
    ],
    "slug": "papaveraceae"
  },
  {
    "name": "Passifloraceae",
    "latin": "Passion Flower family",
    "plants": [
      {
        "slug": "damiana",
        "name": "Damiana"
      },
      {
        "slug": "passionflower",
        "name": "Passionflower"
      }
    ],
    "slug": "passifloraceae"
  },
  {
    "name": "Pedaliaceae",
    "latin": "Sesame family",
    "plants": [
      {
        "slug": "devils-claw",
        "name": "Devil's Claw"
      }
    ],
    "slug": "pedaliaceae"
  },
  {
    "name": "Phormidiaceae",
    "latin": "Cyanobacteria (blue-green algae family)",
    "plants": [
      {
        "slug": "spirulina",
        "name": "Spirulina"
      }
    ],
    "slug": "phormidiaceae"
  },
  {
    "name": "Phyllanthaceae",
    "latin": "Phyllanthus family",
    "plants": [
      {
        "slug": "amla",
        "name": "Amla / Indian Gooseberry"
      }
    ],
    "slug": "phyllanthaceae"
  },
  {
    "name": "Pinaceae",
    "latin": "Pine family",
    "plants": [
      {
        "slug": "pine-needle",
        "name": "Pine Needle"
      }
    ],
    "slug": "pinaceae"
  },
  {
    "name": "Piperaceae",
    "latin": "Pepper family",
    "plants": [
      {
        "slug": "black-pepper",
        "name": "Black Pepper"
      }
    ],
    "slug": "piperaceae"
  },
  {
    "name": "Plantaginaceae",
    "latin": "Plantain family",
    "plants": [
      {
        "slug": "bacopa",
        "name": "Bacopa"
      },
      {
        "slug": "plantain",
        "name": "Plantain"
      }
    ],
    "slug": "plantaginaceae"
  },
  {
    "name": "Poaceae",
    "latin": "Grass family",
    "plants": [
      {
        "slug": "lemongrass",
        "name": "Lemongrass"
      },
      {
        "slug": "oat-straw",
        "name": "Oat Straw"
      },
      {
        "slug": "wheatgrass",
        "name": "Wheatgrass"
      }
    ],
    "slug": "poaceae"
  },
  {
    "name": "Polygonaceae",
    "latin": "Buckwheat family",
    "plants": [
      {
        "slug": "he-shou-wu",
        "name": "He Shou Wu"
      },
      {
        "slug": "yellow-dock",
        "name": "Yellow Dock"
      }
    ],
    "slug": "polygonaceae"
  },
  {
    "name": "Ranunculaceae",
    "latin": "Buttercup family",
    "plants": [
      {
        "slug": "black-cohosh",
        "name": "Black Cohosh"
      },
      {
        "slug": "coptis-goldthread",
        "name": "Coptis / Goldthread"
      },
      {
        "slug": "goldenseal",
        "name": "Goldenseal"
      }
    ],
    "slug": "ranunculaceae"
  },
  {
    "name": "Rhamnaceae",
    "latin": "Buckthorn family",
    "plants": [
      {
        "slug": "red-root",
        "name": "Red Root"
      }
    ],
    "slug": "rhamnaceae"
  },
  {
    "name": "Rosaceae",
    "latin": "Rose family",
    "plants": [
      {
        "slug": "hawthorn",
        "name": "Hawthorn"
      },
      {
        "slug": "meadowsweet",
        "name": "Meadowsweet"
      },
      {
        "slug": "pygeum",
        "name": "Pygeum"
      },
      {
        "slug": "raspberry-leaf",
        "name": "Raspberry Leaf"
      },
      {
        "slug": "rose-hips",
        "name": "Rose Hips"
      },
      {
        "slug": "wild-cherry",
        "name": "Wild Cherry"
      }
    ],
    "slug": "rosaceae"
  },
  {
    "name": "Rubiaceae",
    "latin": "Coffee family",
    "plants": [
      {
        "slug": "cat-s-claw",
        "name": "Cat's Claw"
      },
      {
        "slug": "cleavers",
        "name": "Cleavers"
      },
      {
        "slug": "noni",
        "name": "Noni"
      },
      {
        "slug": "partridge-berry",
        "name": "Partridge Berry"
      }
    ],
    "slug": "rubiaceae"
  },
  {
    "name": "Rutaceae",
    "latin": "Citrus/Rue family",
    "plants": [
      {
        "slug": "buchu",
        "name": "Buchu"
      }
    ],
    "slug": "rutaceae"
  },
  {
    "name": "Salicaceae",
    "latin": "Willow family",
    "plants": [
      {
        "slug": "willow-bark",
        "name": "Willow Bark"
      }
    ],
    "slug": "salicaceae"
  },
  {
    "name": "Sapindaceae",
    "latin": "Soapberry family",
    "plants": [
      {
        "slug": "guarana",
        "name": "Guarana"
      }
    ],
    "slug": "sapindaceae"
  },
  {
    "name": "Schisandraceae",
    "latin": "Schisandra family",
    "plants": [
      {
        "slug": "schisandra",
        "name": "Schisandra"
      },
      {
        "slug": "star-anise",
        "name": "Star Anise"
      }
    ],
    "slug": "schisandraceae"
  },
  {
    "name": "Scrophulariaceae",
    "latin": "Figwort family",
    "plants": [
      {
        "slug": "mullein",
        "name": "Mullein"
      }
    ],
    "slug": "scrophulariaceae"
  },
  {
    "name": "Solanaceae",
    "latin": "Nightshade family",
    "plants": [
      {
        "slug": "ashwagandha",
        "name": "Ashwagandha"
      }
    ],
    "slug": "solanaceae"
  },
  {
    "name": "Theaceae",
    "latin": "Tea family",
    "plants": [
      {
        "slug": "green-tea",
        "name": "Green Tea"
      },
      {
        "slug": "puerh-tea",
        "name": "Pu-erh Tea"
      }
    ],
    "slug": "theaceae"
  },
  {
    "name": "Ulmaceae",
    "latin": "Elm family",
    "plants": [
      {
        "slug": "slippery-elm",
        "name": "Slippery Elm"
      }
    ],
    "slug": "ulmaceae"
  },
  {
    "name": "Urticaceae",
    "latin": "Nettle family",
    "plants": [
      {
        "slug": "nettle",
        "name": "Nettle"
      }
    ],
    "slug": "urticaceae"
  },
  {
    "name": "Verbenaceae",
    "latin": "Verbena family",
    "plants": [
      {
        "slug": "blue-vervain",
        "name": "Blue Vervain"
      },
      {
        "slug": "lemon-verbena",
        "name": "Lemon Verbena"
      }
    ],
    "slug": "verbenaceae"
  },
  {
    "name": "Violaceae",
    "latin": "Violet family",
    "plants": [
      {
        "slug": "violet",
        "name": "Violet"
      }
    ],
    "slug": "violaceae"
  },
  {
    "name": "Zingiberaceae",
    "latin": "Ginger family",
    "plants": [
      {
        "slug": "cardamom",
        "name": "Cardamom"
      },
      {
        "slug": "ginger",
        "name": "Ginger"
      },
      {
        "slug": "turmeric",
        "name": "Turmeric"
      }
    ],
    "slug": "zingiberaceae"
  },
  {
    "name": "Zygophyllaceae",
    "latin": "Caltrop family",
    "plants": [
      {
        "slug": "tribulus",
        "name": "Tribulus"
      }
    ],
    "slug": "zygophyllaceae"
  }
]